multiple_smi/__init__.py
multiple_smi/client/__init__.py
multiple_smi/client/client_smi.py
multiple_smi/client/client_utils.py
multiple_smi/client/menu_frontend/__init__.py
multiple_smi/client/menu_frontend/appindicator.py
multiple_smi/client/menu_frontend/argos.py
multiple_smi/client/menu_frontend/default_frontend.py
multiple_smi/client/menu_frontend/icon_utils.py
multiple_smi/client/notifier_util.py
multiple_smi/client/update_hosts_list.py
multiple_smi/server/__init__.py
multiple_smi/server/install_server_service.py
multiple_smi/server/my_smi.py
multiple_smi/server/server_smi.py
multiple_smi-2.1.0.dist-info/LICENSE
multiple_smi-2.1.0.dist-info/METADATA
multiple_smi-2.1.0.dist-info/WHEEL
multiple_smi-2.1.0.dist-info/entry_points.txt
multiple_smi-2.1.0.dist-info/RECORD
