Metadata-Version: 2.1
Name: Multiple-smi
Version: 2.1.0
Summary: Look up GPU/CPU/RAM usage on multiple servers at the same time
License: MIT
Author: Clément Pinard
Author-email: mail@clementpinard.fr
Requires-Python: >=3.9,<4.0
Classifier: Intended Audience :: Science/Research
Classifier: License :: OSI Approved :: MIT License
Classifier: Programming Language :: Python :: 3
Classifier: Programming Language :: Python :: 3.9
Classifier: Programming Language :: Python :: 3.10
Classifier: Programming Language :: Python :: 3.11
Classifier: Programming Language :: Python :: 3.12
Provides-Extra: client
Provides-Extra: server
Requires-Dist: colorspacious (>=1.1.2,<2.0.0) ; extra == "client"
Requires-Dist: numpy (>=1.26.2,<2.0.0)
Requires-Dist: nvidia-ml-py3 (>=7.352.0,<8.0.0) ; extra == "server"
Requires-Dist: psutil (>=5.9.6,<6.0.0) ; extra == "server" or extra == "server"
Requires-Dist: py-cpuinfo (>=9.0.0,<10.0.0) ; extra == "server"
Requires-Dist: pycairo (>=1.25.1,<2.0.0) ; extra == "client"
Requires-Dist: pygobject (>=3.46.0,<4.0.0) ; extra == "client"
Requires-Dist: python-nmap (>=0.7.1,<0.8.0) ; extra == "client"
Requires-Dist: pyzmq (>=25.1.2,<26.0.0)
